tktl/__init__.py
tktl/constants.py
tktl/login.py
tktl/main.py
tktl/version.py
tktl/cli/__init__.py
tktl/cli/common.py
tktl/cli/delete.py
tktl/cli/get.py
tktl/cli/health.py
tktl/cli/init.py
tktl/cli/lazify.py
tktl/cli/login.py
tktl/cli/run.py
tktl/cli/validate.py
tktl/commands/__init__.py
tktl/commands/deployments.py
tktl/commands/health.py
tktl/commands/init.py
tktl/commands/lazify.py
tktl/commands/login.py
tktl/commands/repositories.py
tktl/commands/run.py
tktl/commands/validate.py
tktl/commands/version.py
tktl/core/__init__.py
tktl/core/config.py
tktl/core/loggers.py
tktl/core/strings.py
tktl/core/t.py
tktl/core/utils.py
tktl/core/validation_messages.py
tktl/core/clients/__init__.py
tktl/core/clients/taktile.py
tktl/core/clients/utils.py
tktl/core/clients/future/__init__.py
tktl/core/clients/future/endpoint.py
tktl/core/clients/future/taktile.py
tktl/core/clients/future/utils.py
tktl/core/exceptions/__init__.py
tktl/core/exceptions/base.py
tktl/core/future/__init__.py
tktl/core/future/t.py
tktl/core/managers/__init__.py
tktl/core/managers/base.py
tktl/core/managers/constants.py
tktl/core/managers/docker.py
tktl/core/managers/model.py
tktl/core/managers/project.py
tktl/core/managers/secrets.py
tktl/core/schemas/__init__.py
tktl/core/schemas/deployment.py
tktl/core/schemas/log.py
tktl/core/schemas/model.py
tktl/core/schemas/project.py
tktl/core/schemas/repository.py
tktl/core/schemas/service.py
tktl/core/schemas/tag.py
tktl/core/schemas/user.py
tktl/core/schemas/utils.py
tktl/core/schemas/future/__init__.py
tktl/core/schemas/future/service.py
tktl/core/serializers/__init__.py
tktl/core/serializers/base.py
tktl/core/serializers/factories.py
tktl/core/serializers/utils.py
tktl/core/serializers/arrow/__init__.py
tktl/core/serializers/arrow/codecs.py
tktl/core/serializers/arrow/factory.py
tktl/core/serializers/arrow/utils.py
tktl/core/serializers/rest/__init__.py
tktl/core/serializers/rest/factory.py
tktl/core/serializers/rest/schema.py
taktile_cli-1.5.15.dist-info/LICENSE
taktile_cli-1.5.15.dist-info/METADATA
taktile_cli-1.5.15.dist-info/WHEEL
taktile_cli-1.5.15.dist-info/entry_points.txt
taktile_cli-1.5.15.dist-info/top_level.txt
taktile_cli-1.5.15.dist-info/RECORD
