Metadata-Version: 2.1
Name: taktile-cli
Version: 1.5.15
Summary: Taktile's CLI 
Home-page: https://docs.taktile.com
Author: Taktile GmbH
Author-email: devops@taktile.com
License: Apache License 2.0
Keywords: taktile-cli
Classifier: Intended Audience :: Developers
Classifier: License :: OSI Approved :: Apache Software License
Classifier: Programming Language :: Python :: 3.7
Classifier: Programming Language :: Python :: 3.8
Classifier: Programming Language :: Python :: 3.9
Classifier: Programming Language :: Python :: 3.10
Requires-Python: >=3.7, <3.11
License-File: LICENSE
Requires-Dist: click ~=8.0.4
Requires-Dist: click-completion ~=0.5.2
Requires-Dist: click-help-colors ~=0.9.1
Requires-Dist: click-didyoumean ~=0.0.3
Requires-Dist: requests ~=2.23
Requires-Dist: pydantic ~=1.8.2
Requires-Dist: colorama ~=0.4.3
Requires-Dist: PyYAML >=6.0.0
Requires-Dist: python-dateutil ~=2.8.1
Requires-Dist: halo ==0.0.29
Requires-Dist: numpy ~=1.21
Requires-Dist: pandas ~=1.2
Requires-Dist: pyarrow >=3.0
Requires-Dist: beautifultable ~=1.0.0
Requires-Dist: openapi-schema-pydantic ==1.1.0
Requires-Dist: docker ==4.3.1
Requires-Dist: tenacity <9.0.0,>=8.0.1
Requires-Dist: cached-property ==1.5.2
Requires-Dist: fastapi ~=0.65.2
Requires-Dist: taktile-types <1.0.0,>=0.22.0
Requires-Dist: packaging <24.0,>=23.0
Requires-Dist: taktile-client ~=1.0.6
Requires-Dist: filelock >=3.5.0
Requires-Dist: urllib3 <2
